marine_qc/__init__.py
marine_qc/astronomical_geometry.py
marine_qc/auxiliary.py
marine_qc/buoy_tracking_qc.py
marine_qc/calculate_humidity.py
marine_qc/external_clim.py
marine_qc/location_control.py
marine_qc/multiple_row_checks.py
marine_qc/plot_qc_outcomes.py
marine_qc/qc_grouped_reports.py
marine_qc/qc_individual_reports.py
marine_qc/qc_sequential_reports.py
marine_qc/spherical_geometry.py
marine_qc/statistics.py
marine_qc/time_control.py
marine_qc/track_check_utils.py
marine_qc-0.2.0.dist-info/licenses/LICENSE
marine_qc-0.2.0.dist-info/WHEEL
marine_qc-0.2.0.dist-info/METADATA
marine_qc-0.2.0.dist-info/RECORD
