Metadata-Version: 2.4
Name: marine_qc
Version: 0.2.0
Summary: Marine Quality Control package.
Keywords: marine_qc
Author-email: Ludwig Lierhammer <ludwig.lierhammer@dwd.de>, John Kennedy <jjk8932@googlemail.com>, Tina Leiding <tina.leiding@dwd.de>, Kate Willett <kate.willett@metoffice.gov.uk>, Chris Atkinson <chris.atkinson@metoffice.gov.uk>, Richard Cornes <richard.cornes@noc.ac.uk>, Elizabeth Kent <eck@noc.ac.uk>, Trevor James Smith <smith.trevorj@ouranos.ca>, Axel Andersson <axel.andersson@dwd.de>
Maintainer-email: Ludwig Lierhammer <ludwig.lierhammer@dwd.de>, John Kennedy <jjk8932@googlemail.com>
Requires-Python: >=3.10.0
License-Expression: Apache-2.0
Classifier: Development Status :: 1 - Planning
Classifier: Intended Audience :: Developers
Classifier: Intended Audience :: Science/Research
Classifier: Natural Language :: English
Classifier: Operating System :: OS Independent
Classifier: Programming Language :: Python :: 3
Classifier: Programming Language :: Python :: 3.10
Classifier: Programming Language :: Python :: 3.11
Classifier: Programming Language :: Python :: 3.12
Classifier: Programming Language :: Python :: 3.13
License-File: LICENSE
Requires-Dist: cdm_reader_mapper
Requires-Dist: cf_xarray
Requires-Dist: matplotlib
Requires-Dist: pyproj
Requires-Dist: xclim
Requires-Dist: marine_qc[dev] ; extra == "all"
Requires-Dist: marine_qc[docs] ; extra == "all"
Requires-Dist: bump-my-version >=1.2.3 ; extra == "dev"
Requires-Dist: codespell ==2.4.1 ; extra == "dev"
Requires-Dist: coverage >=7.5.0 ; extra == "dev"
Requires-Dist: deptry >=0.23.1 ; extra == "dev"
Requires-Dist: flake8 >=7.3.0 ; extra == "dev"
Requires-Dist: flake8-rst-docstrings >=0.3.1 ; extra == "dev"
Requires-Dist: flit >=3.11.0,<4.0 ; extra == "dev"
Requires-Dist: mypy >=1.18.2 ; extra == "dev"
Requires-Dist: notebook ; extra == "dev"
Requires-Dist: numpydoc >=1.9.0 ; extra == "dev"
Requires-Dist: pip >=25.2 ; extra == "dev"
Requires-Dist: pre-commit >=3.7.0 ; extra == "dev"
Requires-Dist: pylint >=3.3.1 ; extra == "dev"
Requires-Dist: pytest >=8.3.4 ; extra == "dev"
Requires-Dist: pytest-cov >=6.0.0 ; extra == "dev"
Requires-Dist: pytest-env >=1.1.5 ; extra == "dev"
Requires-Dist: ruff >=0.13.3 ; extra == "dev"
Requires-Dist: tox >=4.30.3 ; extra == "dev"
Requires-Dist: vulture >=2.14 ; extra == "dev"
Requires-Dist: watchdog >=4.0.0 ; extra == "dev"
Requires-Dist: ipykernel ; extra == "docs"
Requires-Dist: ipython >=8.5.0 ; extra == "docs"
Requires-Dist: jupyter_client ; extra == "docs"
Requires-Dist: myst-nb >=1.2.0 ; extra == "docs"
Requires-Dist: nbconvert >=7.16.4 ; extra == "docs"
Requires-Dist: numpydoc >=1.9.0 ; extra == "docs"
Requires-Dist: sphinx >=7.1.0,<8.2 ; extra == "docs"
Requires-Dist: sphinx-autodoc-typehints ; extra == "docs"
Requires-Dist: sphinx-copybutton ; extra == "docs"
Requires-Dist: sphinx-book-theme >=1.0 ; extra == "docs"
Project-URL: Changelog, https://marine_qc.readthedocs.io/en/stable/changelog.html
Project-URL: Homepage, https://marine-qc.readthedocs.io
Project-URL: Issue tracker, https://github.com/glamod/marine_qc
Project-URL: Source, https://github.com/glamod/marine_qc
Provides-Extra: all
Provides-Extra: dev
Provides-Extra: docs
